[
  {
    "Sentence":"Ich beneide meine Nachbarin f\u00fcr ihren sch\u00f6nen",
    "Target_word":"hals",
    "WordPredictions":1,
    "wn":8.0,
    "nwords":14,
    "nprt":59,
    "nw":8,
    "sn":207,
    "cloze":0.0169491525,
    "entropy":1.3616997689,
    "condition":"em_lc",
    "sn_rand":247,
    "sn_0":247,
    "Prior":"em",
    "Sentences":"s_em_247p.wav",
    "Target_word.1":"s_em_lc_247tw",
    "randomization":0.6527513471,
    "Web_Audio":"s_em_247p.wav",
    "Single_Word":"s_em_lc_247tw_6.wav",
    "sentence":"Stimuli\/s_em_247p.wav",
    "word":"Stimuli\/s_em_lc_247tw_6.wav",
    "randomize_1":0.0008490348
  },
  {
    "Sentence":"Sie strengte sich an, aber erkannte keine",
    "Target_word":"muster",
    "WordPredictions":8,
    "wn":26.0,
    "nwords":41,
    "nprt":67,
    "nw":8,
    "sn":331,
    "cloze":0.1194029851,
    "entropy":3.4896190677,
    "condition":"eh",
    "sn_rand":400,
    "sn_0":400,
    "Prior":"eh",
    "Sentences":"s_eh_400p.wav",
    "Target_word.1":"s_eh_400tw",
    "randomization":0.2004780713,
    "Web_Audio":"s_eh_400p.wav",
    "Single_Word":"s_eh_400tw_1.wav",
    "sentence":"Stimuli\/s_eh_400p.wav",
    "word":"Stimuli\/s_eh_400tw_1.wav",
    "randomize_1":0.0115102218
  },
  {
    "Sentence":"Ihr Gro\u00dfvater vererbte ihr seine wertvolle",
    "Target_word":"uhr",
    "WordPredictions":36,
    "wn":11.0,
    "nwords":12,
    "nprt":68,
    "nw":7,
    "sn":216,
    "cloze":0.5294117647,
    "entropy":1.5846546782,
    "condition":"em_hc",
    "sn_rand":259,
    "sn_0":259,
    "Prior":"em",
    "Sentences":"s_em_259p.wav",
    "Target_word.1":"s_em_hc_259tw",
    "randomization":0.3292269224,
    "Web_Audio":"s_em_259p.wav",
    "Single_Word":"s_em_hc_259tw_3.wav",
    "sentence":"Stimuli\/s_em_259p.wav",
    "word":"Stimuli\/s_em_hc_259tw_3.wav",
    "randomize_1":0.012113632
  },
  {
    "Sentence":"Die alte Dame sitzt auf der Parkbank und f\u00fcttert die",
    "Target_word":"tauben",
    "WordPredictions":28,
    "wn":7.0,
    "nwords":8,
    "nprt":68,
    "nw":11,
    "sn":149,
    "cloze":0.4117647059,
    "entropy":1.3995705288,
    "condition":"em_hc",
    "sn_rand":164,
    "sn_0":164,
    "Prior":"em",
    "Sentences":"s_em_164p.wav",
    "Target_word.1":"s_em_hc_164tw",
    "randomization":0.2700807647,
    "Web_Audio":"s_em_164p.wav",
    "Single_Word":"s_em_hc_164tw_3.wav",
    "sentence":"Stimuli\/s_em_164p.wav",
    "word":"Stimuli\/s_em_hc_164tw_3.wav",
    "randomize_1":0.0195360279
  },
  {
    "Sentence":"Der Fluss durch die Stadt f\u00fchrt direkt zum",
    "Target_word":"meer",
    "WordPredictions":31,
    "wn":6.0,
    "nwords":16,
    "nprt":66,
    "nw":9,
    "sn":99,
    "cloze":0.4696969697,
    "entropy":1.8240528217,
    "condition":"em_hc",
    "sn_rand":107,
    "sn_0":107,
    "Prior":"em",
    "Sentences":"s_em_107p.wav",
    "Target_word.1":"s_em_hc_107tw",
    "randomization":0.7969668342,
    "Web_Audio":"s_em_107p.wav",
    "Single_Word":"s_em_hc_107tw_12.wav",
    "sentence":"Stimuli\/s_em_107p.wav",
    "word":"Stimuli\/s_em_hc_107tw_12.wav",
    "randomize_1":0.0238477894
  },
  {
    "Sentence":"Sie wischte sich den Schwei\u00df von der",
    "Target_word":"stirn",
    "WordPredictions":65,
    "wn":4.0,
    "nwords":4,
    "nprt":68,
    "nw":8,
    "sn":333,
    "cloze":0.9558823529,
    "entropy":0.2292845795,
    "condition":"el",
    "sn_rand":402,
    "sn_0":402,
    "Prior":"el",
    "Sentences":"s_el_402p.wav",
    "Target_word.1":"s_el_402tw",
    "randomization":0.1473950974,
    "Web_Audio":"s_el_402p.wav",
    "Single_Word":"s_el_402tw_1.wav",
    "sentence":"Stimuli\/s_el_402p.wav",
    "word":"Stimuli\/s_el_402tw_1.wav",
    "randomize_1":0.0299191796
  },
  {
    "Sentence":"Zur Belohnung gebe ich meinem Hund ein",
    "Target_word":"leckerli",
    "WordPredictions":60,
    "wn":2.0,
    "nwords":2,
    "nprt":61,
    "nw":8,
    "sn":360,
    "cloze":0.9836065574,
    "entropy":0.0836497046,
    "condition":"el",
    "sn_rand":441,
    "sn_0":441,
    "Prior":"el",
    "Sentences":"s_el_441p.wav",
    "Target_word.1":"s_el_441tw",
    "randomization":0.8443069821,
    "Web_Audio":"s_el_441p.wav",
    "Single_Word":"s_el_441tw_12.wav",
    "sentence":"Stimuli\/s_el_441p.wav",
    "word":"Stimuli\/s_el_441tw_12.wav",
    "randomize_1":0.0325791696
  },
  {
    "Sentence":"Auf der Ladefl\u00e4che des Transporters befand sich eine",
    "Target_word":"kiste",
    "WordPredictions":14,
    "wn":10.0,
    "nwords":35,
    "nprt":68,
    "nw":9,
    "sn":32,
    "cloze":0.2058823529,
    "entropy":3.1891912452,
    "condition":"eh",
    "sn_rand":27,
    "sn_0":27,
    "Prior":"eh",
    "Sentences":"s_eh_027p.wav",
    "Target_word.1":"s_eh_027tw",
    "randomization":0.6681154522,
    "Web_Audio":"s_eh_027p.wav",
    "Single_Word":"s_eh_027tw_6.wav",
    "sentence":"Stimuli\/s_eh_027p.wav",
    "word":"Stimuli\/s_eh_027tw_6.wav",
    "randomize_1":0.036610222
  },
  {
    "Sentence":"Immer mehr Jugendliche nehmen leichtsinnigerweise ",
    "Target_word":"Drogen ",
    "WordPredictions":43,
    "wn":null,
    "nwords":2,
    "nprt":44,
    "nw":6,
    "sn":25,
    "cloze":0.9772727273,
    "entropy":0.108471339,
    "condition":"el",
    "sn_rand":297,
    "sn_0":297,
    "Prior":"el",
    "Sentences":"s_el_297p.wav",
    "Target_word.1":"s_el_297tw",
    "randomization":0.4711132996,
    "Web_Audio":"s_el_297p.wav",
    "Single_Word":"s_el_297tw_6.wav",
    "sentence":"Stimuli\/s_el_297p.wav",
    "word":"Stimuli\/s_el_297tw_6.wav",
    "randomize_1":0.038563601
  },
  {
    "Sentence":"Der Park in der N\u00e4he hat einen gro\u00dfen",
    "Target_word":"see",
    "WordPredictions":28,
    "wn":7.0,
    "nwords":9,
    "nprt":67,
    "nw":9,
    "sn":126,
    "cloze":0.4179104478,
    "entropy":1.5629156615,
    "condition":"em_hc",
    "sn_rand":130,
    "sn_0":130,
    "Prior":"em",
    "Sentences":"s_em_130p.wav",
    "Target_word.1":"s_em_hc_130tw",
    "randomization":0.1615924176,
    "Web_Audio":"s_em_130p.wav",
    "Single_Word":"s_em_hc_130tw_1.wav",
    "sentence":"Stimuli\/s_em_130p.wav",
    "word":"Stimuli\/s_em_hc_130tw_1.wav",
    "randomize_1":0.045025511
  },
  {
    "Sentence":"Ungeduldig schaut Toni auf ihre",
    "Target_word":"kuh",
    "WordPredictions":0,
    "wn":5.0,
    "nwords":5,
    "nprt":76,
    "nw":6,
    "sn":22,
    "cloze":0.0,
    "entropy":0.3742793428,
    "condition":"el_mm",
    "sn_rand":415,
    "sn_0":415,
    "Prior":"el",
    "Sentences":"s_el_415p.wav",
    "Target_word.1":"s_el_mm_415tw",
    "randomization":0.005993606,
    "Web_Audio":"s_el_415p.wav",
    "Single_Word":"s_el_mm_415tw_1.wav",
    "sentence":"Stimuli\/s_el_415p.wav",
    "word":"Stimuli\/s_el_mm_415tw_1.wav",
    "randomize_1":0.0535670865
  },
  {
    "Sentence":"Zur Bekr\u00e4ftigung des Friedens rauchten die Indianer eine",
    "Target_word":"Feige",
    "WordPredictions":0,
    "wn":null,
    "nwords":2,
    "nprt":44,
    "nw":9,
    "sn":37,
    "cloze":0.0,
    "entropy":0.4741393131,
    "condition":"el_mm",
    "sn_rand":439,
    "sn_0":439,
    "Prior":"el",
    "Sentences":"s_el_439p.wav",
    "Target_word.1":"s_el_mm_439tw",
    "randomization":0.2530658463,
    "Web_Audio":"s_el_439p.wav",
    "Single_Word":"s_el_mm_439tw_3.wav",
    "sentence":"Stimuli\/s_el_439p.wav",
    "word":"Stimuli\/s_el_mm_439tw_3.wav",
    "randomize_1":0.0691844955
  },
  {
    "Sentence":"Auf einer Mission untersuchten die Astronauten die Oberfl\u00e4che des",
    "Target_word":"raumschiffs",
    "WordPredictions":2,
    "wn":7.0,
    "nwords":7,
    "nprt":67,
    "nw":10,
    "sn":36,
    "cloze":0.0298507463,
    "entropy":1.0275604427,
    "condition":"em_lc",
    "sn_rand":31,
    "sn_0":31,
    "Prior":"em",
    "Sentences":"s_em_031p.wav",
    "Target_word.1":"s_em_lc_031tw",
    "randomization":0.594118985,
    "Web_Audio":"s_em_031p.wav",
    "Single_Word":"s_em_lc_031tw_6.wav",
    "sentence":"Stimuli\/s_em_031p.wav",
    "word":"Stimuli\/s_em_lc_031tw_6.wav",
    "randomize_1":0.0719606803
  },
  {
    "Sentence":"Im Streichelzoo gibt es freche",
    "Target_word":"igel",
    "WordPredictions":1,
    "wn":5.0,
    "nwords":11,
    "nprt":65,
    "nw":6,
    "sn":238,
    "cloze":0.0153846154,
    "entropy":1.4351002836,
    "condition":"em_lc",
    "sn_rand":285,
    "sn_0":285,
    "Prior":"em",
    "Sentences":"s_em_285p.wav",
    "Target_word.1":"s_em_lc_285tw",
    "randomization":0.6834309473,
    "Web_Audio":"s_em_285p.wav",
    "Single_Word":"s_em_lc_285tw_6.wav",
    "sentence":"Stimuli\/s_em_285p.wav",
    "word":"Stimuli\/s_em_lc_285tw_6.wav",
    "randomize_1":0.0765670455
  },
  {
    "Sentence":"Zum Angeln spie\u00dfte sie den Wurm auf den",
    "Target_word":"haken",
    "WordPredictions":64,
    "wn":3.0,
    "nwords":6,
    "nprt":76,
    "nw":9,
    "sn":25,
    "cloze":0.8421052632,
    "entropy":0.6436950374,
    "condition":"el",
    "sn_rand":437,
    "sn_0":437,
    "Prior":"el",
    "Sentences":"s_el_437p.wav",
    "Target_word.1":"s_el_437tw",
    "randomization":0.6820303141,
    "Web_Audio":"s_el_437p.wav",
    "Single_Word":"s_el_437tw_6.wav",
    "sentence":"Stimuli\/s_el_437p.wav",
    "word":"Stimuli\/s_el_437tw_6.wav",
    "randomize_1":0.08838812
  },
  {
    "Sentence":"Die Forscherin entdeckt eine neue Pflanzenart im",
    "Target_word":"dschungel",
    "WordPredictions":16,
    "wn":7.0,
    "nwords":21,
    "nprt":66,
    "nw":8,
    "sn":157,
    "cloze":0.2424242424,
    "entropy":2.51322942,
    "condition":"eh",
    "sn_rand":183,
    "sn_0":183,
    "Prior":"eh",
    "Sentences":"s_eh_183p.wav",
    "Target_word.1":"s_eh_183tw",
    "randomization":0.0485086155,
    "Web_Audio":"s_eh_183p.wav",
    "Single_Word":"s_eh_183tw_1.wav",
    "sentence":"Stimuli\/s_eh_183p.wav",
    "word":"Stimuli\/s_eh_183tw_1.wav",
    "randomize_1":0.0884228891
  },
  {
    "Sentence":"Der fr\u00fche Vogel f\u00e4ngt den",
    "Target_word":"luchs",
    "WordPredictions":0,
    "wn":1.0,
    "nwords":1,
    "nprt":66,
    "nw":6,
    "sn":100,
    "cloze":0.0,
    "entropy":0.0,
    "condition":"el_mm",
    "sn_rand":109,
    "sn_0":109,
    "Prior":"el",
    "Sentences":"s_el_109p.wav",
    "Target_word.1":"s_el_mm_109tw",
    "randomization":0.1975431442,
    "Web_Audio":"s_el_109p.wav",
    "Single_Word":"s_el_mm_109tw_1.wav",
    "sentence":"Stimuli\/s_el_109p.wav",
    "word":"Stimuli\/s_el_mm_109tw_1.wav",
    "randomize_1":0.092072333
  },
  {
    "Sentence":"Der Fahrer f\u00e4hrt die Staatsg\u00e4ste sicher durch die",
    "Target_word":"nacht",
    "WordPredictions":1,
    "wn":11.0,
    "nwords":16,
    "nprt":68,
    "nw":9,
    "sn":95,
    "cloze":0.0147058824,
    "entropy":1.5438510912,
    "condition":"em_lc",
    "sn_rand":100,
    "sn_0":100,
    "Prior":"em",
    "Sentences":"s_em_100p.wav",
    "Target_word.1":"s_em_lc_100tw",
    "randomization":0.1777520562,
    "Web_Audio":"s_em_100p.wav",
    "Single_Word":"s_em_lc_100tw_1.wav",
    "sentence":"Stimuli\/s_em_100p.wav",
    "word":"Stimuli\/s_em_lc_100tw_1.wav",
    "randomize_1":0.1027305088
  },
  {
    "Sentence":"Der Plan hat Hand und ",
    "Target_word":"Fu\u00df ",
    "WordPredictions":46,
    "wn":null,
    "nwords":1,
    "nprt":46,
    "nw":6,
    "sn":8,
    "cloze":1.0,
    "entropy":0.0,
    "condition":"el",
    "sn_rand":133,
    "sn_0":133,
    "Prior":"el",
    "Sentences":"s_el_133p.wav",
    "Target_word.1":"s_el_133tw",
    "randomization":0.0141707247,
    "Web_Audio":"s_el_133p.wav",
    "Single_Word":"s_el_133tw_1.wav",
    "sentence":"Stimuli\/s_el_133p.wav",
    "word":"Stimuli\/s_el_133tw_1.wav",
    "randomize_1":0.1071701338
  },
  {
    "Sentence":"Nach der Gartenarbeit wusch sie sich gr\u00fcndlich die",
    "Target_word":"achseln",
    "WordPredictions":0,
    "wn":2.0,
    "nwords":2,
    "nprt":76,
    "nw":9,
    "sn":17,
    "cloze":0.0,
    "entropy":0.1216924027,
    "condition":"el_mm",
    "sn_rand":370,
    "sn_0":370,
    "Prior":"el",
    "Sentences":"s_el_370p.wav",
    "Target_word.1":"s_el_mm_370tw",
    "randomization":0.1994696262,
    "Web_Audio":"s_el_370p.wav",
    "Single_Word":"s_el_mm_370tw_1.wav",
    "sentence":"Stimuli\/s_el_370p.wav",
    "word":"Stimuli\/s_el_mm_370tw_1.wav",
    "randomize_1":0.1074059264
  },
  {
    "Sentence":"Der Zauberer verriet dem Publikum seinen ",
    "Target_word":"weg",
    "WordPredictions":0,
    "wn":null,
    "nwords":4,
    "nprt":47,
    "nw":7,
    "sn":11,
    "cloze":0.0,
    "entropy":0.2054707498,
    "condition":"el_mm",
    "sn_rand":160,
    "sn_0":160,
    "Prior":"el",
    "Sentences":"s_el_160p.wav",
    "Target_word.1":"s_el_mm_160tw",
    "randomization":0.4437121538,
    "Web_Audio":"s_el_160p.wav",
    "Single_Word":"s_el_mm_160tw_3.wav",
    "sentence":"Stimuli\/s_el_160p.wav",
    "word":"Stimuli\/s_el_mm_160tw_3.wav",
    "randomize_1":0.1131375763
  },
  {
    "Sentence":"Der Fernseher im Wohnzimmer hat einen gro\u00dfen",
    "Target_word":"sprung",
    "WordPredictions":1,
    "wn":12.0,
    "nwords":12,
    "nprt":67,
    "nw":8,
    "sn":96,
    "cloze":0.0149253731,
    "entropy":1.0710121538,
    "condition":"em_lc",
    "sn_rand":102,
    "sn_0":102,
    "Prior":"em",
    "Sentences":"s_em_102p.wav",
    "Target_word.1":"s_em_lc_102tw",
    "randomization":0.4361848386,
    "Web_Audio":"s_em_102p.wav",
    "Single_Word":"s_em_lc_102tw_3.wav",
    "sentence":"Stimuli\/s_em_102p.wav",
    "word":"Stimuli\/s_em_lc_102tw_3.wav",
    "randomize_1":0.1149818052
  },
  {
    "Sentence":"Der Skilift schaukelte bedenklich im",
    "Target_word":"wind",
    "WordPredictions":64,
    "wn":7.0,
    "nwords":7,
    "nprt":76,
    "nw":6,
    "sn":7,
    "cloze":0.8421052632,
    "entropy":0.6688205967,
    "condition":"el",
    "sn_rand":140,
    "sn_0":140,
    "Prior":"el",
    "Sentences":"s_el_140p.wav",
    "Target_word.1":"s_el_140tw",
    "randomization":0.6027014202,
    "Web_Audio":"s_el_140p.wav",
    "Single_Word":"s_el_140tw_6.wav",
    "sentence":"Stimuli\/s_el_140p.wav",
    "word":"Stimuli\/s_el_140tw_6.wav",
    "randomize_1":0.1191398769
  },
  {
    "Sentence":"Sie kam mit den Beinen kaum bis auf den ",
    "Target_word":"Kessel",
    "WordPredictions":0,
    "wn":null,
    "nwords":4,
    "nprt":45,
    "nw":10,
    "sn":35,
    "cloze":0.0,
    "entropy":0.3923791765,
    "condition":"el_mm",
    "sn_rand":396,
    "sn_0":396,
    "Prior":"el",
    "Sentences":"s_el_396p.wav",
    "Target_word.1":"s_el_mm_396tw",
    "randomization":0.4195835841,
    "Web_Audio":"s_el_396p.wav",
    "Single_Word":"s_el_mm_396tw_3.wav",
    "sentence":"Stimuli\/s_el_396p.wav",
    "word":"Stimuli\/s_el_mm_396tw_3.wav",
    "randomize_1":0.1255565794
  },
  {
    "Sentence":"Im Zoo f\u00fcttern die Tierpfleger die hungrigen",
    "Target_word":"l\u00f6wen",
    "WordPredictions":30,
    "wn":7.0,
    "nwords":14,
    "nprt":68,
    "nw":8,
    "sn":244,
    "cloze":0.4411764706,
    "entropy":1.825659958,
    "condition":"em_hc",
    "sn_rand":293,
    "sn_0":293,
    "Prior":"em",
    "Sentences":"s_em_293p.wav",
    "Target_word.1":"s_em_hc_293tw",
    "randomization":0.7187832142,
    "Web_Audio":"s_em_293p.wav",
    "Single_Word":"s_em_hc_293tw_6.wav",
    "sentence":"Stimuli\/s_em_293p.wav",
    "word":"Stimuli\/s_em_hc_293tw_6.wav",
    "randomize_1":0.1292879253
  },
  {
    "Sentence":"Die Kellnerin serviert den Nachtisch auf dem",
    "Target_word":"tablett",
    "WordPredictions":42,
    "wn":6.0,
    "nwords":10,
    "nprt":65,
    "nw":8,
    "sn":169,
    "cloze":0.6461538462,
    "entropy":1.2724592437,
    "condition":"em_hc",
    "sn_rand":195,
    "sn_0":195,
    "Prior":"em",
    "Sentences":"s_em_195p.wav",
    "Target_word.1":"s_em_hc_195tw",
    "randomization":0.0151607991,
    "Web_Audio":"s_em_195p.wav",
    "Single_Word":"s_em_hc_195tw_1.wav",
    "sentence":"Stimuli\/s_em_195p.wav",
    "word":"Stimuli\/s_em_hc_195tw_1.wav",
    "randomize_1":0.1316629531
  },
  {
    "Sentence":"Im Sandkasten spielen die Kinder mit Schaufel und",
    "Target_word":"gabel",
    "WordPredictions":1,
    "wn":5.0,
    "nwords":10,
    "nprt":68,
    "nw":9,
    "sn":236,
    "cloze":0.0147058824,
    "entropy":1.3343446166,
    "condition":"em_lc",
    "sn_rand":283,
    "sn_0":283,
    "Prior":"em",
    "Sentences":"s_em_283p.wav",
    "Target_word.1":"s_em_lc_283tw",
    "randomization":0.260781385,
    "Web_Audio":"s_em_283p.wav",
    "Single_Word":"s_em_lc_283tw_1.wav",
    "sentence":"Stimuli\/s_em_283p.wav",
    "word":"Stimuli\/s_em_lc_283tw_1.wav",
    "randomize_1":0.1332165475
  },
  {
    "Sentence":"Die Kaffeetasse auf dem Tisch hat ein Muster mit",
    "Target_word":"blumen",
    "WordPredictions":25,
    "wn":2.0,
    "nwords":26,
    "nprt":68,
    "nw":10,
    "sn":167,
    "cloze":0.3676470588,
    "entropy":2.6052793629,
    "condition":"eh",
    "sn_rand":192,
    "sn_0":192,
    "Prior":"eh",
    "Sentences":"s_eh_192p.wav",
    "Target_word.1":"s_eh_192tw",
    "randomization":0.8548813053,
    "Web_Audio":"s_eh_192p.wav",
    "Single_Word":"s_eh_192tw_6.wav",
    "sentence":"Stimuli\/s_eh_192p.wav",
    "word":"Stimuli\/s_eh_192tw_6.wav",
    "randomize_1":0.1398153986
  },
  {
    "Sentence":"Wir planen am Wochenende einen",
    "Target_word":"umtrunk",
    "WordPredictions":1,
    "wn":9.0,
    "nwords":10,
    "nprt":65,
    "nw":6,
    "sn":351,
    "cloze":0.0153846154,
    "entropy":0.9442858669,
    "condition":"em_lc",
    "sn_rand":427,
    "sn_0":427,
    "Prior":"em",
    "Sentences":"s_em_427p.wav",
    "Target_word.1":"s_em_lc_427tw",
    "randomization":0.5002182233,
    "Web_Audio":"s_em_427p.wav",
    "Single_Word":"s_em_lc_427tw_3.wav",
    "sentence":"Stimuli\/s_em_427p.wav",
    "word":"Stimuli\/s_em_lc_427tw_3.wav",
    "randomize_1":0.148995256
  },
  {
    "Sentence":"Ich suche meine Schl\u00fcssel in der",
    "Target_word":"tasche",
    "WordPredictions":39,
    "wn":9.0,
    "nwords":10,
    "nprt":66,
    "nw":7,
    "sn":213,
    "cloze":0.5909090909,
    "entropy":1.4362873424,
    "condition":"em_hc",
    "sn_rand":253,
    "sn_0":253,
    "Prior":"em",
    "Sentences":"s_em_253p.wav",
    "Target_word.1":"s_em_hc_253tw",
    "randomization":0.4587709866,
    "Web_Audio":"s_em_253p.wav",
    "Single_Word":"s_em_hc_253tw_6.wav",
    "sentence":"Stimuli\/s_em_253p.wav",
    "word":"Stimuli\/s_em_hc_253tw_6.wav",
    "randomize_1":0.1606812161
  },
  {
    "Sentence":"Trotz der Turbulenzen bringt der Pilot das Flugzeug sicher nach",
    "Target_word":"hause",
    "WordPredictions":30,
    "wn":6.0,
    "nwords":15,
    "nprt":66,
    "nw":11,
    "sn":336,
    "cloze":0.4545454545,
    "entropy":1.6250073252,
    "condition":"em_hc",
    "sn_rand":406,
    "sn_0":406,
    "Prior":"em",
    "Sentences":"s_em_406p.wav",
    "Target_word.1":"s_em_hc_406tw",
    "randomization":0.2574494535,
    "Web_Audio":"s_em_406p.wav",
    "Single_Word":"s_em_hc_406tw_3.wav",
    "sentence":"Stimuli\/s_em_406p.wav",
    "word":"Stimuli\/s_em_hc_406tw_3.wav",
    "randomize_1":0.1685853531
  },
  {
    "Sentence":"Aus dem Fenster sieht man in der Ferne die hohen",
    "Target_word":"masten",
    "WordPredictions":1,
    "wn":6.0,
    "nwords":9,
    "nprt":64,
    "nw":11,
    "sn":41,
    "cloze":0.015625,
    "entropy":1.2298077215,
    "condition":"em_lc",
    "sn_rand":37,
    "sn_0":37,
    "Prior":"em",
    "Sentences":"s_em_037p.wav",
    "Target_word.1":"s_em_lc_037tw",
    "randomization":0.1482296204,
    "Web_Audio":"s_em_037p.wav",
    "Single_Word":"s_em_lc_037tw_1.wav",
    "sentence":"Stimuli\/s_em_037p.wav",
    "word":"Stimuli\/s_em_lc_037tw_1.wav",
    "randomize_1":0.1708479057
  },
  {
    "Sentence":"Beim Kochen schnitt sich Onur in den",
    "Target_word":"finger",
    "WordPredictions":61,
    "wn":3.0,
    "nwords":5,
    "nprt":68,
    "nw":8,
    "sn":57,
    "cloze":0.8970588235,
    "entropy":0.4629571619,
    "condition":"el",
    "sn_rand":50,
    "sn_0":50,
    "Prior":"el",
    "Sentences":"s_el_050p.wav",
    "Target_word.1":"s_el_050tw",
    "randomization":0.9844461188,
    "Web_Audio":"s_el_050p.wav",
    "Single_Word":"s_el_050tw_12.wav",
    "sentence":"Stimuli\/s_el_050p.wav",
    "word":"Stimuli\/s_el_050tw_12.wav",
    "randomize_1":0.1720234772
  },
  {
    "Sentence":"In einer Seeschlacht erbeuteten die Piraten viele",
    "Target_word":"sch\u00e4tze",
    "WordPredictions":36,
    "wn":16.0,
    "nwords":22,
    "nprt":68,
    "nw":8,
    "sn":272,
    "cloze":0.5294117647,
    "entropy":2.0459131734,
    "condition":"em_hc",
    "sn_rand":323,
    "sn_0":323,
    "Prior":"em",
    "Sentences":"s_em_323p.wav",
    "Target_word.1":"s_em_hc_323tw",
    "randomization":0.7762756566,
    "Web_Audio":"s_em_323p.wav",
    "Single_Word":"s_em_hc_323tw_12.wav",
    "sentence":"Stimuli\/s_em_323p.wav",
    "word":"Stimuli\/s_em_hc_323tw_12.wav",
    "randomize_1":0.1824961438
  },
  {
    "Sentence":"Kurz vor der Ziellinie fiel der Reiter von seinem",
    "Target_word":"strau\u00df",
    "WordPredictions":0,
    "wn":1.0,
    "nwords":3,
    "nprt":66,
    "nw":10,
    "sn":287,
    "cloze":0.0,
    "entropy":0.2138398614,
    "condition":"el_mm",
    "sn_rand":342,
    "sn_0":342,
    "Prior":"el",
    "Sentences":"s_el_342p.wav",
    "Target_word.1":"s_el_mm_342tw",
    "randomization":0.3593520907,
    "Web_Audio":"s_el_342p.wav",
    "Single_Word":"s_el_mm_342tw_3.wav",
    "sentence":"Stimuli\/s_el_342p.wav",
    "word":"Stimuli\/s_el_mm_342tw_3.wav",
    "randomize_1":0.2052733557
  },
  {
    "Sentence":"Auf dem Oktoberfest trinken die Menschen viel",
    "Target_word":"bier",
    "WordPredictions":64,
    "wn":2.0,
    "nwords":2,
    "nprt":66,
    "nw":8,
    "sn":21,
    "cloze":0.9696969697,
    "entropy":0.1357939588,
    "condition":"el",
    "sn_rand":17,
    "sn_0":17,
    "Prior":"el",
    "Sentences":"s_el_017p.wav",
    "Target_word.1":"s_el_017tw",
    "randomization":0.9465771296,
    "Web_Audio":"s_el_017p.wav",
    "Single_Word":"s_el_017tw_12.wav",
    "sentence":"Stimuli\/s_el_017p.wav",
    "word":"Stimuli\/s_el_017tw_12.wav",
    "randomize_1":0.2160321595
  },
  {
    "Sentence":"Meine Pommes esse ich am liebsten mit Ketchup und",
    "Target_word":"salat",
    "WordPredictions":0,
    "wn":1.0,
    "nwords":1,
    "nprt":76,
    "nw":10,
    "sn":16,
    "cloze":0.0,
    "entropy":0.0,
    "condition":"el_mm",
    "sn_rand":352,
    "sn_0":352,
    "Prior":"el",
    "Sentences":"s_el_352p.wav",
    "Target_word.1":"s_el_mm_352tw",
    "randomization":0.4962386414,
    "Web_Audio":"s_el_352p.wav",
    "Single_Word":"s_el_mm_352tw_6.wav",
    "sentence":"Stimuli\/s_el_352p.wav",
    "word":"Stimuli\/s_el_mm_352tw_6.wav",
    "randomize_1":0.2190757129
  },
  {
    "Sentence":"Mit voller Wucht traf die Abrissbirne das",
    "Target_word":"regal",
    "WordPredictions":1,
    "wn":7.0,
    "nwords":7,
    "nprt":67,
    "nw":8,
    "sn":303,
    "cloze":0.0149253731,
    "entropy":1.0282179549,
    "condition":"em_lc",
    "sn_rand":359,
    "sn_0":359,
    "Prior":"em",
    "Sentences":"s_em_359p.wav",
    "Target_word.1":"s_em_lc_359tw",
    "randomization":0.8045725892,
    "Web_Audio":"s_em_359p.wav",
    "Single_Word":"s_em_lc_359tw_12.wav",
    "sentence":"Stimuli\/s_em_359p.wav",
    "word":"Stimuli\/s_em_lc_359tw_12.wav",
    "randomize_1":0.2203148758
  },
  {
    "Sentence":"An Weihnachten schm\u00fcckte die ganze Familie den Baum mit",
    "Target_word":"kugeln",
    "WordPredictions":39,
    "wn":7.0,
    "nwords":13,
    "nprt":65,
    "nw":10,
    "sn":16,
    "cloze":0.6,
    "entropy":1.4535154687,
    "condition":"em_hc",
    "sn_rand":11,
    "sn_0":11,
    "Prior":"em",
    "Sentences":"s_em_011p.wav",
    "Target_word.1":"s_em_hc_011tw",
    "randomization":0.139336561,
    "Web_Audio":"s_em_011p.wav",
    "Single_Word":"s_em_hc_011tw_1.wav",
    "sentence":"Stimuli\/s_em_011p.wav",
    "word":"Stimuli\/s_em_hc_011tw_1.wav",
    "randomize_1":0.222118152
  },
  {
    "Sentence":"Der Schaffner wurde misstrauisch wegen des",
    "Target_word":"tickets",
    "WordPredictions":23,
    "wn":23.0,
    "nwords":26,
    "nprt":66,
    "nw":7,
    "sn":130,
    "cloze":0.3484848485,
    "entropy":2.6389840404,
    "condition":"eh",
    "sn_rand":136,
    "sn_0":136,
    "Prior":"eh",
    "Sentences":"s_eh_136p.wav",
    "Target_word.1":"s_eh_136tw",
    "randomization":0.8771816952,
    "Web_Audio":"s_eh_136p.wav",
    "Single_Word":"s_eh_136tw_12.wav",
    "sentence":"Stimuli\/s_eh_136p.wav",
    "word":"Stimuli\/s_eh_136tw_12.wav",
    "randomize_1":0.2350321435
  },
  {
    "Sentence":"Die Hose war zu eng zum",
    "Target_word":"sitzen",
    "WordPredictions":16,
    "wn":16.0,
    "nwords":20,
    "nprt":66,
    "nw":7,
    "sn":162,
    "cloze":0.2424242424,
    "entropy":2.5510136778,
    "condition":"eh",
    "sn_rand":185,
    "sn_0":185,
    "Prior":"eh",
    "Sentences":"s_eh_185p.wav",
    "Target_word.1":"s_eh_185tw",
    "randomization":0.4484569386,
    "Web_Audio":"s_eh_185p.wav",
    "Single_Word":"s_eh_185tw_3.wav",
    "sentence":"Stimuli\/s_eh_185p.wav",
    "word":"Stimuli\/s_eh_185tw_3.wav",
    "randomize_1":0.2560081112
  },
  {
    "Sentence":"Ihre Arbeit machte ihr ",
    "Target_word":"Spa\u00df",
    "WordPredictions":45,
    "wn":null,
    "nwords":2,
    "nprt":52,
    "nw":5,
    "sn":23,
    "cloze":0.8653846154,
    "entropy":0.3950671208,
    "condition":"el",
    "sn_rand":263,
    "sn_0":263,
    "Prior":"el",
    "Sentences":"s_el_263p.wav",
    "Target_word.1":"s_el_263tw",
    "randomization":0.2361744658,
    "Web_Audio":"s_el_263p.wav",
    "Single_Word":"s_el_263tw_3.wav",
    "sentence":"Stimuli\/s_el_263p.wav",
    "word":"Stimuli\/s_el_263tw_3.wav",
    "randomize_1":0.265444226
  },
  {
    "Sentence":"In den Bergen \u00fcbernachten die G\u00e4ste in einer gem\u00fctlichen",
    "Target_word":"h\u00fctte",
    "WordPredictions":50,
    "wn":3.0,
    "nwords":9,
    "nprt":66,
    "nw":10,
    "sn":250,
    "cloze":0.7575757576,
    "entropy":1.0159563499,
    "condition":"em_hc",
    "sn_rand":304,
    "sn_0":304,
    "Prior":"em",
    "Sentences":"s_em_304p.wav",
    "Target_word.1":"s_em_hc_304tw",
    "randomization":0.7415174823,
    "Web_Audio":"s_em_304p.wav",
    "Single_Word":"s_em_hc_304tw_6.wav",
    "sentence":"Stimuli\/s_em_304p.wav",
    "word":"Stimuli\/s_em_hc_304tw_6.wav",
    "randomize_1":0.2657689405
  },
  {
    "Sentence":"Die italienische Mafia handelt vor allem mit",
    "Target_word":"k\u00f6pfchen",
    "WordPredictions":1,
    "wn":6.0,
    "nwords":11,
    "nprt":68,
    "nw":8,
    "sn":163,
    "cloze":0.0147058824,
    "entropy":1.1332467773,
    "condition":"em_lc",
    "sn_rand":186,
    "sn_0":186,
    "Prior":"em",
    "Sentences":"s_em_186p.wav",
    "Target_word.1":"s_em_lc_186tw",
    "randomization":0.8861626245,
    "Web_Audio":"s_em_186p.wav",
    "Single_Word":"s_em_lc_186tw_12.wav",
    "sentence":"Stimuli\/s_em_186p.wav",
    "word":"Stimuli\/s_em_lc_186tw_12.wav",
    "randomize_1":0.2685084932
  },
  {
    "Sentence":"Der Baum im Herbst hat bunte",
    "Target_word":"schleifen",
    "WordPredictions":0,
    "wn":1.0,
    "nwords":1,
    "nprt":66,
    "nw":7,
    "sn":89,
    "cloze":0.0,
    "entropy":0.0,
    "condition":"el_mm",
    "sn_rand":91,
    "sn_0":91,
    "Prior":"el",
    "Sentences":"s_el_091p.wav",
    "Target_word.1":"s_el_mm_091tw",
    "randomization":0.2032951374,
    "Web_Audio":"s_el_091p.wav",
    "Single_Word":"s_el_mm_091tw_1.wav",
    "sentence":"Stimuli\/s_el_091p.wav",
    "word":"Stimuli\/s_el_mm_091tw_1.wav",
    "randomize_1":0.2704010547
  },
  {
    "Sentence":"Die lange steile Treppe f\u00fchrt zum",
    "Target_word":"dachboden",
    "WordPredictions":17,
    "wn":8.0,
    "nwords":29,
    "nprt":66,
    "nw":7,
    "sn":174,
    "cloze":0.2575757576,
    "entropy":2.8641060748,
    "condition":"eh",
    "sn_rand":203,
    "sn_0":203,
    "Prior":"eh",
    "Sentences":"s_eh_203p.wav",
    "Target_word.1":"s_eh_203tw",
    "randomization":0.1907437186,
    "Web_Audio":"s_eh_203p.wav",
    "Single_Word":"s_eh_203tw_1.wav",
    "sentence":"Stimuli\/s_eh_203p.wav",
    "word":"Stimuli\/s_eh_203tw_1.wav",
    "randomize_1":0.2729097457
  },
  {
    "Sentence":"Das Cappie sch\u00fctzt die Augen vor der",
    "Target_word":"kreide",
    "WordPredictions":0,
    "wn":2.0,
    "nwords":3,
    "nprt":65,
    "nw":8,
    "sn":65,
    "cloze":0.0,
    "entropy":0.2657850763,
    "condition":"el_mm",
    "sn_rand":64,
    "sn_0":64,
    "Prior":"el",
    "Sentences":"s_el_064p.wav",
    "Target_word.1":"s_el_mm_064tw",
    "randomization":0.5184143957,
    "Web_Audio":"s_el_064p.wav",
    "Single_Word":"s_el_mm_064tw_6.wav",
    "sentence":"Stimuli\/s_el_064p.wav",
    "word":"Stimuli\/s_el_mm_064tw_6.wav",
    "randomize_1":0.2760717249
  },
  {
    "Sentence":"Im Aquarium gibt es neben Fischen auch",
    "Target_word":"pflanzen",
    "WordPredictions":11,
    "wn":12.0,
    "nwords":24,
    "nprt":65,
    "nw":8,
    "sn":220,
    "cloze":0.1692307692,
    "entropy":2.792576662,
    "condition":"eh",
    "sn_rand":267,
    "sn_0":267,
    "Prior":"eh",
    "Sentences":"s_eh_267p.wav",
    "Target_word.1":"s_eh_267tw",
    "randomization":0.4007194567,
    "Web_Audio":"s_eh_267p.wav",
    "Single_Word":"s_eh_267tw_3.wav",
    "sentence":"Stimuli\/s_eh_267p.wav",
    "word":"Stimuli\/s_eh_267tw_3.wav",
    "randomize_1":0.2775054353
  },
  {
    "Sentence":"Aus der Mine hoben die Bergarbeiter wertvolles",
    "Target_word":"kupfer",
    "WordPredictions":1,
    "wn":9.0,
    "nwords":13,
    "nprt":65,
    "nw":8,
    "sn":46,
    "cloze":0.0153846154,
    "entropy":1.6358239043,
    "condition":"em_lc",
    "sn_rand":43,
    "sn_0":43,
    "Prior":"em",
    "Sentences":"s_em_043p.wav",
    "Target_word.1":"s_em_lc_043tw",
    "randomization":0.7492756334,
    "Web_Audio":"s_em_043p.wav",
    "Single_Word":"s_em_lc_043tw_12.wav",
    "sentence":"Stimuli\/s_em_043p.wav",
    "word":"Stimuli\/s_em_lc_043tw_12.wav",
    "randomize_1":0.2778611782
  },
  {
    "Sentence":"Im Kindergarten bekamen die meisten Kinder in dieser Woche",
    "Target_word":"l\u00e4use",
    "WordPredictions":5,
    "wn":20.0,
    "nwords":38,
    "nprt":67,
    "nw":10,
    "sn":229,
    "cloze":0.0746268657,
    "entropy":3.4406947125,
    "condition":"eh",
    "sn_rand":278,
    "sn_0":278,
    "Prior":"eh",
    "Sentences":"s_eh_278p.wav",
    "Target_word.1":"s_eh_278tw",
    "randomization":0.1772021324,
    "Web_Audio":"s_eh_278p.wav",
    "Single_Word":"s_eh_278tw_1.wav",
    "sentence":"Stimuli\/s_eh_278p.wav",
    "word":"Stimuli\/s_eh_278tw_1.wav",
    "randomize_1":0.2810770194
  }
]